odoo/addons/product_pricelist_item_list_view/README.rst
odoo/addons/product_pricelist_item_list_view/__init__.py
odoo/addons/product_pricelist_item_list_view/__manifest__.py
odoo/addons/product_pricelist_item_list_view/i18n/ca.po
odoo/addons/product_pricelist_item_list_view/i18n/de.po
odoo/addons/product_pricelist_item_list_view/i18n/es.po
odoo/addons/product_pricelist_item_list_view/i18n/fr.po
odoo/addons/product_pricelist_item_list_view/i18n/it.po
odoo/addons/product_pricelist_item_list_view/i18n/product_pricelist_item_list_view.pot
odoo/addons/product_pricelist_item_list_view/readme/CONTRIBUTORS.md
odoo/addons/product_pricelist_item_list_view/readme/CREDITS.md
odoo/addons/product_pricelist_item_list_view/readme/DESCRIPTION.md
odoo/addons/product_pricelist_item_list_view/readme/USAGE.md
odoo/addons/product_pricelist_item_list_view/static/description/icon.png
odoo/addons/product_pricelist_item_list_view/static/description/index.html
odoo/addons/product_pricelist_item_list_view/views/pricelist_view.xml
odoo_addon_product_pricelist_item_list_view-18.0.1.0.0.2.dist-info/METADATA
odoo_addon_product_pricelist_item_list_view-18.0.1.0.0.2.dist-info/WHEEL
odoo_addon_product_pricelist_item_list_view-18.0.1.0.0.2.dist-info/top_level.txt
odoo_addon_product_pricelist_item_list_view-18.0.1.0.0.2.dist-info/RECORD
