Metadata-Version: 2.1
Name: odoo-addon-product_pricelist_item_list_view
Version: 18.0.1.0.0.2
Requires-Python: >=3.10
Requires-Dist: odoo==18.0.*
Summary: View and search the list of pricelist items
Home-page: https://github.com/OCA/product-attribute
License: LGPL-3
Author: Agile Business Group, ForgeFlow, Odoo Community Association (OCA)
Author-email: support@odoo-community.org
Classifier: Programming Language :: Python
Classifier: Framework :: Odoo
Classifier: Framework :: Odoo :: 18.0
Classifier: License :: OSI Approved :: GNU Lesser General Public License v3 (LGPLv3)
Classifier: Development Status :: 5 - Production/Stable
